[
  {
    "label": "BASELINE (4C=2)",
    "cycles": 1880,
    "sessions": 59,
    "gpf": 1.2302,
    "npf": 1.1724,
    "net_pnl": 18944.0,
    "mean_daily": 321.1,
    "std_daily": 798.1,
    "sharpe": 0.4023,
    "session_win_pct": 0.678,
    "worst_day": -1556.0,
    "max_dd": -1585.0,
    "max_cycle_loss": -943.0,
    "stopped_4c": 99,
    "stopped_regime": 0,
    "cap_walks": 829,
    "clean_pct": 0.4335
  },
  {
    "label": "NO_STOPS",
    "cycles": 1847,
    "sessions": 59,
    "gpf": 1.2597,
    "npf": 1.1997,
    "net_pnl": 20919.0,
    "mean_daily": 354.6,
    "std_daily": 806.9,
    "sharpe": 0.4394,
    "session_win_pct": 0.6949,
    "worst_day": -2210.0,
    "max_dd": -2210.0,
    "max_cycle_loss": -1385.0,
    "stopped_4c": 0,
    "stopped_regime": 0,
    "cap_walks": 894,
    "clean_pct": 0.4396
  },
  {
    "label": "H1a: tight=1, normal=2, wide=3",
    "cycles": 3490,
    "sessions": 59,
    "gpf": 1.1281,
    "npf": 1.0748,
    "net_pnl": 16022.0,
    "mean_daily": 271.6,
    "std_daily": 1271.2,
    "sharpe": 0.2136,
    "session_win_pct": 0.6271,
    "worst_day": -2801.0,
    "max_dd": -6491.0,
    "max_cycle_loss": -943.0,
    "stopped_4c": 226,
    "stopped_regime": 226,
    "cap_walks": 1752,
    "clean_pct": 0.4367
  },
  {
    "label": "H1b: tight=1, normal=2",
    "cycles": 3498,
    "sessions": 59,
    "gpf": 1.1119,
    "npf": 1.0597,
    "net_pnl": 13029.0,
    "mean_daily": 220.8,
    "std_daily": 1185.8,
    "sharpe": 0.1862,
    "session_win_pct": 0.5932,
    "worst_day": -2801.0,
    "max_dd": -5548.0,
    "max_cycle_loss": -934.0,
    "stopped_4c": 265,
    "stopped_regime": 265,
    "cap_walks": 1724,
    "clean_pct": 0.4345
  },
  {
    "label": "H1c: tight=1, normal=3",
    "cycles": 3481,
    "sessions": 59,
    "gpf": 1.1371,
    "npf": 1.0834,
    "net_pnl": 17691.0,
    "mean_daily": 299.8,
    "std_daily": 1257.9,
    "sharpe": 0.2384,
    "session_win_pct": 0.6102,
    "worst_day": -2378.0,
    "max_dd": -5581.0,
    "max_cycle_loss": -1221.0,
    "stopped_4c": 130,
    "stopped_regime": 130,
    "cap_walks": 1824,
    "clean_pct": 0.4418
  },
  {
    "label": "H1d: compressed=0(flat), normal=2, wide=3",
    "cycles": 3465,
    "sessions": 59,
    "gpf": 1.0906,
    "npf": 1.0393,
    "net_pnl": 8595.0,
    "mean_daily": 145.7,
    "std_daily": 1212.9,
    "sharpe": 0.1201,
    "session_win_pct": 0.5593,
    "worst_day": -2889.0,
    "max_dd": -6052.0,
    "max_cycle_loss": -1116.0,
    "stopped_4c": 189,
    "stopped_regime": 189,
    "cap_walks": 1811,
    "clean_pct": 0.4303
  },
  {
    "label": "H2: MAE > 1.5*P90",
    "cycles": 4102,
    "sessions": 59,
    "gpf": 1.0122,
    "npf": 0.9624,
    "net_pnl": -9807.0,
    "mean_daily": -166.2,
    "std_daily": 1028.0,
    "sharpe": -0.1617,
    "session_win_pct": 0.4237,
    "worst_day": -3380.0,
    "max_dd": -11382.0,
    "max_cycle_loss": -744.0,
    "stopped_4c": 0,
    "stopped_regime": 1335,
    "cap_walks": 1,
    "clean_pct": 0.4242
  },
  {
    "label": "H2: MAE > 2.0*P90",
    "cycles": 3868,
    "sessions": 59,
    "gpf": 1.1461,
    "npf": 1.0927,
    "net_pnl": 22040.0,
    "mean_daily": 373.6,
    "std_daily": 1182.6,
    "sharpe": 0.3159,
    "session_win_pct": 0.5763,
    "worst_day": -1631.0,
    "max_dd": -6050.0,
    "max_cycle_loss": -744.0,
    "stopped_4c": 0,
    "stopped_regime": 793,
    "cap_walks": 1092,
    "clean_pct": 0.4374
  },
  {
    "label": "H2: MAE > 2.5*P90",
    "cycles": 3731,
    "sessions": 59,
    "gpf": 1.1433,
    "npf": 1.0896,
    "net_pnl": 20457.0,
    "mean_daily": 346.7,
    "std_daily": 1281.5,
    "sharpe": 0.2706,
    "session_win_pct": 0.6441,
    "worst_day": -3404.0,
    "max_dd": -5825.0,
    "max_cycle_loss": -744.0,
    "stopped_4c": 0,
    "stopped_regime": 543,
    "cap_walks": 1076,
    "clean_pct": 0.4369
  },
  {
    "label": "H2: MAE > 3.0*P90",
    "cycles": 3559,
    "sessions": 59,
    "gpf": 1.1055,
    "npf": 1.0531,
    "net_pnl": 11729.0,
    "mean_daily": 198.8,
    "std_daily": 1153.1,
    "sharpe": 0.1724,
    "session_win_pct": 0.5085,
    "worst_day": -1920.0,
    "max_dd": -4854.0,
    "max_cycle_loss": -744.0,
    "stopped_4c": 0,
    "stopped_regime": 370,
    "cap_walks": 1552,
    "clean_pct": 0.4324
  },
  {
    "label": "H2: MAE > 3.5*P90",
    "cycles": 3613,
    "sessions": 59,
    "gpf": 1.1493,
    "npf": 1.0954,
    "net_pnl": 20947.0,
    "mean_daily": 355.0,
    "std_daily": 1226.5,
    "sharpe": 0.2895,
    "session_win_pct": 0.5932,
    "worst_day": -1982.0,
    "max_dd": -3728.0,
    "max_cycle_loss": -852.0,
    "stopped_4c": 5,
    "stopped_regime": 270,
    "cap_walks": 1511,
    "clean_pct": 0.442
  },
  {
    "label": "H3: MAE > 2.0*P75",
    "cycles": 4068,
    "sessions": 59,
    "gpf": 1.0228,
    "npf": 0.972,
    "net_pnl": -7146.0,
    "mean_daily": -121.1,
    "std_daily": 1372.3,
    "sharpe": -0.0883,
    "session_win_pct": 0.3898,
    "worst_day": -6138.0,
    "max_dd": -9499.0,
    "max_cycle_loss": -322.0,
    "stopped_4c": 0,
    "stopped_regime": 1328,
    "cap_walks": 0,
    "clean_pct": 0.4213
  },
  {
    "label": "H3: MAE > 2.5*P75",
    "cycles": 3842,
    "sessions": 59,
    "gpf": 1.0835,
    "npf": 1.0333,
    "net_pnl": 8193.0,
    "mean_daily": 138.9,
    "std_daily": 1215.0,
    "sharpe": 0.1143,
    "session_win_pct": 0.4746,
    "worst_day": -2634.0,
    "max_dd": -3873.0,
    "max_cycle_loss": -744.0,
    "stopped_4c": 0,
    "stopped_regime": 949,
    "cap_walks": 1057,
    "clean_pct": 0.4368
  },
  {
    "label": "H3: MAE > 3.0*P75",
    "cycles": 3786,
    "sessions": 59,
    "gpf": 1.1089,
    "npf": 1.0569,
    "net_pnl": 13470.0,
    "mean_daily": 228.3,
    "std_daily": 1214.5,
    "sharpe": 0.188,
    "session_win_pct": 0.5763,
    "worst_day": -2287.0,
    "max_dd": -5374.0,
    "max_cycle_loss": -744.0,
    "stopped_4c": 0,
    "stopped_regime": 674,
    "cap_walks": 1109,
    "clean_pct": 0.4358
  },
  {
    "label": "H3: MAE > 3.5*P75",
    "cycles": 3679,
    "sessions": 59,
    "gpf": 1.1602,
    "npf": 1.1058,
    "net_pnl": 23574.0,
    "mean_daily": 399.6,
    "std_daily": 1285.6,
    "sharpe": 0.3108,
    "session_win_pct": 0.6102,
    "worst_day": -2466.0,
    "max_dd": -5453.0,
    "max_cycle_loss": -744.0,
    "stopped_4c": 0,
    "stopped_regime": 508,
    "cap_walks": 1077,
    "clean_pct": 0.4395
  },
  {
    "label": "H3: MAE > 4.0*P75",
    "cycles": 3589,
    "sessions": 59,
    "gpf": 1.1144,
    "npf": 1.0616,
    "net_pnl": 13656.0,
    "mean_daily": 231.5,
    "std_daily": 1289.8,
    "sharpe": 0.1795,
    "session_win_pct": 0.5932,
    "worst_day": -3431.0,
    "max_dd": -6614.0,
    "max_cycle_loss": -744.0,
    "stopped_4c": 0,
    "stopped_regime": 389,
    "cap_walks": 1533,
    "clean_pct": 0.431
  },
  {
    "label": "H4: cap=1 when P90/P75>1.2",
    "cycles": 3455,
    "sessions": 59,
    "gpf": 1.1495,
    "npf": 1.0952,
    "net_pnl": 13005.0,
    "mean_daily": 220.4,
    "std_daily": 789.2,
    "sharpe": 0.2793,
    "session_win_pct": 0.6271,
    "worst_day": -1610.0,
    "max_dd": -3349.0,
    "max_cycle_loss": -535.0,
    "stopped_4c": 379,
    "stopped_regime": 379,
    "cap_walks": 3023,
    "clean_pct": 0.9948
  },
  {
    "label": "H4: cap=1 when P90/P75>1.3",
    "cycles": 3450,
    "sessions": 59,
    "gpf": 1.1475,
    "npf": 1.0923,
    "net_pnl": 13843.0,
    "mean_daily": 234.6,
    "std_daily": 878.9,
    "sharpe": 0.267,
    "session_win_pct": 0.6102,
    "worst_day": -1546.0,
    "max_dd": -2956.0,
    "max_cycle_loss": -786.0,
    "stopped_4c": 339,
    "stopped_regime": 339,
    "cap_walks": 2766,
    "clean_pct": 0.8707
  },
  {
    "label": "H4: cap=1 when P90/P75>1.4",
    "cycles": 3467,
    "sessions": 59,
    "gpf": 1.1255,
    "npf": 1.0713,
    "net_pnl": 13736.0,
    "mean_daily": 232.8,
    "std_daily": 1207.6,
    "sharpe": 0.1928,
    "session_win_pct": 0.6271,
    "worst_day": -3068.0,
    "max_dd": -6341.0,
    "max_cycle_loss": -887.0,
    "stopped_4c": 258,
    "stopped_regime": 258,
    "cap_walks": 2061,
    "clean_pct": 0.5593
  },
  {
    "label": "H4: cap=1 when P90/P75>1.5",
    "cycles": 3460,
    "sessions": 59,
    "gpf": 1.104,
    "npf": 1.0521,
    "net_pnl": 11183.0,
    "mean_daily": 189.5,
    "std_daily": 1205.7,
    "sharpe": 0.1572,
    "session_win_pct": 0.6102,
    "worst_day": -2801.0,
    "max_dd": -7277.0,
    "max_cycle_loss": -944.0,
    "stopped_4c": 226,
    "stopped_regime": 226,
    "cap_walks": 1784,
    "clean_pct": 0.4439
  },
  {
    "label": "H5: skip add if P90>1.1x entry",
    "cycles": 3475,
    "sessions": 59,
    "gpf": 1.1048,
    "npf": 1.0527,
    "net_pnl": 11405.0,
    "mean_daily": 193.3,
    "std_daily": 1204.9,
    "sharpe": 0.1604,
    "session_win_pct": 0.6102,
    "worst_day": -2801.0,
    "max_dd": -7133.0,
    "max_cycle_loss": -943.0,
    "stopped_4c": 222,
    "stopped_regime": 222,
    "cap_walks": 1773,
    "clean_pct": 0.4351
  },
  {
    "label": "H5: skip add if P90>1.2x entry",
    "cycles": 3475,
    "sessions": 59,
    "gpf": 1.1052,
    "npf": 1.053,
    "net_pnl": 11485.0,
    "mean_daily": 194.7,
    "std_daily": 1205.1,
    "sharpe": 0.1615,
    "session_win_pct": 0.6102,
    "worst_day": -2801.0,
    "max_dd": -7133.0,
    "max_cycle_loss": -943.0,
    "stopped_4c": 222,
    "stopped_regime": 222,
    "cap_walks": 1773,
    "clean_pct": 0.4348
  },
  {
    "label": "H5: skip add if P90>1.3x entry",
    "cycles": 3475,
    "sessions": 59,
    "gpf": 1.1052,
    "npf": 1.053,
    "net_pnl": 11485.0,
    "mean_daily": 194.7,
    "std_daily": 1205.1,
    "sharpe": 0.1615,
    "session_win_pct": 0.6102,
    "worst_day": -2801.0,
    "max_dd": -7133.0,
    "max_cycle_loss": -943.0,
    "stopped_4c": 222,
    "stopped_regime": 222,
    "cap_walks": 1773,
    "clean_pct": 0.4348
  },
  {
    "label": "H5: skip add if P90>1.5x entry",
    "cycles": 3475,
    "sessions": 59,
    "gpf": 1.1052,
    "npf": 1.053,
    "net_pnl": 11485.0,
    "mean_daily": 194.7,
    "std_daily": 1205.1,
    "sharpe": 0.1615,
    "session_win_pct": 0.6102,
    "worst_day": -2801.0,
    "max_dd": -7133.0,
    "max_cycle_loss": -943.0,
    "stopped_4c": 222,
    "stopped_regime": 222,
    "cap_walks": 1773,
    "clean_pct": 0.4348
  }
]